aloeschema/__init__.py
aloeschema/constant.py
aloeschema/error.py
aloeschema/validator.py
aloeschema-0.1.0.dist-info/licenses/LICENSE
aloeschema-0.1.0.dist-info/METADATA
aloeschema-0.1.0.dist-info/WHEEL
aloeschema-0.1.0.dist-info/top_level.txt
aloeschema-0.1.0.dist-info/RECORD
