Metadata-Version: 2.4
Name: aloeschema
Version: 0.1.0
Summary: AloeSchema is a simple schema.org accessor and validator that allows custom types and properties
Author-email: michael@aloecraft.org
Maintainer-email: michael@aloecraft.org
License-Expression: Apache-2.0
Requires-Python: >=3.9
License-File: LICENSE
Requires-Dist: requests
Provides-Extra: test
Requires-Dist: pytest>=6.0; extra == "test"
Requires-Dist: coverage; extra == "test"
Dynamic: license-file
